classify_chimeras/__init__.py
classify_chimeras/example.py
classify_chimeras/stencil_1d.py
classify_chimeras/stencil_2d.py
classify_chimeras/utils.py
classify_chimeras-2.0.2.dist-info/LICENSE
classify_chimeras-2.0.2.dist-info/METADATA
classify_chimeras-2.0.2.dist-info/WHEEL
classify_chimeras-2.0.2.dist-info/top_level.txt
classify_chimeras-2.0.2.dist-info/RECORD
