Metadata-Version: 2.1
Name: classify_chimeras
Version: 2.0.2
Summary: Chimera states in nonlocally-coupled phase oscillators
Home-page: http://github.com/fkemeth/classify_chimeras
Author: Felix P. Kemeth
Author-email: felix@kemeth.de
License: GPL-3.0
Project-URL: Bug Tracker, https://github.com/fkemeth/classify_chimeras/issues
Classifier: License :: OSI Approved :: GNU General Public License v3 (GPLv3)
Classifier: Operating System :: OS Independent
Classifier: Programming Language :: Python :: 3
Classifier: Programming Language :: Python :: 3 :: Only
Classifier: Programming Language :: Python :: 3.6
Classifier: Programming Language :: Python :: 3.7
Classifier: Programming Language :: Python :: 3.8
Classifier: Programming Language :: Python :: 3.9
Classifier: Programming Language :: Python :: 3.10
Classifier: Programming Language :: Python :: 3.11
Classifier: Programming Language :: Python :: 3.12
Requires-Python: >=3.6
License-File: LICENSE
